README.md
procrun.py
setup.py
procrun.egg-info/PKG-INFO
procrun.egg-info/SOURCES.txt
procrun.egg-info/dependency_links.txt
procrun.egg-info/top_level.txt