Metadata-Version: 1.0
Name: procrun
Version: 1.6.0
Summary: procrun: process runner
Home-page: https://github.com/val-labs/procrun
Author: UNKNOWN
Author-email: UNKNOWN
License: MIT
Platform: any
